socketutils/__init__.py
socketutils/utils.py
mysocketuntils-0.0.1.dist-info/LICENSE
mysocketuntils-0.0.1.dist-info/METADATA
mysocketuntils-0.0.1.dist-info/WHEEL
mysocketuntils-0.0.1.dist-info/top_level.txt
mysocketuntils-0.0.1.dist-info/RECORD
