Metadata-Version: 2.1
Name: mysocketuntils
Version: 0.0.1
Summary: mysocketutils
Home-page: https://gitee.com/zidanewenqsh/socketutils
Author: ai-046
Author-email: phznai_046@163.com
License: UNKNOWN
Project-URL: Bug Tracker, https://gitee.com/zidanewenqsh/socketutils
Platform: UNKNOWN
Classifier: Programming Language :: Python :: 3
Classifier: License :: OSI Approved :: MIT License
Classifier: Operating System :: OS Independent
Requires-Python: >=3.6
License-File: LICENSE
